.coveragerc
.mailmap
.testr.conf
.travis.yml
AUTHORS
CONTRIBUTING.rst
ChangeLog
HACKING.rst
LICENSE
MANIFEST.in
README.rst
babel.cfg
coverage.sh
requirements.txt
run_functional_tests.sh
setup.cfg
setup.py
test-requirements.txt
tox.ini
ci/Dockerfile.test
ci/application.conf
ci/deploy_sjs.sh
ci/log4j-server.properties
ci/run_ft_in_docker.sh
ci/start.sh
doc/source/conf.py
doc/source/contributing.rst
doc/source/index.rst
doc/source/installation.rst
doc/source/readme.rst
doc/source/usage.rst
doc/source/ref/index.rst
python_sjsclient.egg-info/PKG-INFO
python_sjsclient.egg-info/SOURCES.txt
python_sjsclient.egg-info/dependency_links.txt
python_sjsclient.egg-info/not-zip-safe
python_sjsclient.egg-info/pbr.json
python_sjsclient.egg-info/requires.txt
python_sjsclient.egg-info/top_level.txt
sjsclient/__init__.py
sjsclient/app.py
sjsclient/base.py
sjsclient/client.py
sjsclient/context.py
sjsclient/exceptions.py
sjsclient/job.py
sjsclient/utils.py
sjsclient/tests/__init__.py
sjsclient/tests/base.py
sjsclient/tests/test_sjsclient.py
sjsclient/tests/functional/__init__.py
sjsclient/tests/functional/base.py
sjsclient/tests/functional/test_app.py
sjsclient/tests/functional/test_context.py
sjsclient/tests/functional/test_job.py
sjsclient/tests/unit/__init__.py
sjsclient/tests/unit/test_app.py
sjsclient/tests/unit/test_base.py
sjsclient/tests/unit/test_client.py
sjsclient/tests/unit/test_context.py
sjsclient/tests/unit/test_exceptions.py
sjsclient/tests/unit/test_job.py